stpd/__init__.py
stpd/utils_geocode.py
stpd/version.py
stpd/event/__init__.py
stpd/event/_event.py
stpd/fourier/__init__.py
stpd/fourier/_fourier.py
stpd/nytsentiment/__init__.py
stpd/nytsentiment/_nytsentiment.py
stpd/openrouteservice/__init__.py
stpd/openrouteservice/_openrouteservice.py
stpd/openstreetmap/__init__.py
stpd/openstreetmap/_openstreetmap.py
stpd/openstreetmap/_osm_features.py
SpaceTimePandas-0.3.3.dist-info/LICENSE
SpaceTimePandas-0.3.3.dist-info/METADATA
SpaceTimePandas-0.3.3.dist-info/WHEEL
SpaceTimePandas-0.3.3.dist-info/top_level.txt
SpaceTimePandas-0.3.3.dist-info/RECORD
