Metadata-Version: 2.1
Name: SpaceTimePandas
Version: 0.3.3
Summary: Location date features as dataframe
Home-page: https://github.com/tianle91/SpaceTimePandas
Author: Tianle Chen
Author-email: tianlechen@gmail.com
Classifier: Programming Language :: Python :: 3
Classifier: License :: OSI Approved :: MIT License
Classifier: Operating System :: OS Independent
Requires-Python: >=3.7
License-File: LICENSE
Requires-Dist: geopy (>=2.1.0)
Requires-Dist: holidays (>=0.14.2)
Requires-Dist: openrouteservice (>=2.3.3)
Requires-Dist: OSMPythonTools (>=0.3.5)
Requires-Dist: pynytimes (>=0.7.0)
